{"name":"Tor Browser Portable","tagline":"Portable version of the Tor Browser, for Windows","body":"# Tor Browser Portable\r\n\r\nTor Browser Portable is the Tor Browser packaged with a PortableApps.com launcher as a portable app, so you can browse in privacy on your iPod, USB flash drive, portable hard drive, etc. It has all the same features as Tor Browser, plus, it leaves no personal information behind on the machine you run it on, so you can take it with you wherever you go.\r\n\r\n## System Requirements\r\n\r\n* Microsoft Windows 8, 7, Vista or XP.\r\n* [PortableApps.com Platform](http://portableapps.com/download) (Optional)\r\n\r\n## Credits\r\n\r\n* Tor Browser Portable is a redistribution of the [Tor Browser Bundle](https://www.torproject.org/projects/torbrowser.html).\r\n\r\n## License\r\n\r\n* Portable application code released under [the MIT license](LICENSE).\r\n* The Tor Browser Bundle is released under [its various licenses](TorBrowserPortable/App/TorBrowser/TorBrowser/Docs/Licenses).","google":"","note":"Don't delete this file! It's used internally to help with page regeneration."}